findpkg/__init__.py
findpkg/__main__.py
findpkg-0.1.2.dist-info/licenses/LICENSE
findpkg-0.1.2.dist-info/METADATA
findpkg-0.1.2.dist-info/WHEEL
findpkg-0.1.2.dist-info/entry_points.txt
findpkg-0.1.2.dist-info/top_level.txt
findpkg-0.1.2.dist-info/RECORD
