Metadata-Version: 2.4
Name: findpkg
Version: 0.1.2
Summary: CLI tool to locate in which virtual environment a Python package is installed.
Home-page: https://github.com/Pro-Ace-grammer/findpkg
Author: Arslaan Darwajkar
Classifier: Programming Language :: Python :: 3
Classifier: License :: OSI Approved :: MIT License
Classifier: Operating System :: OS Independent
Requires-Python: >=3.6
License-File: LICENSE
Dynamic: author
Dynamic: classifier
Dynamic: description
Dynamic: description-content-type
Dynamic: home-page
Dynamic: license-file
Dynamic: requires-python
Dynamic: summary
